ask_human_for_context_mcp/__init__.py
ask_human_for_context_mcp/__main__.py
ask_human_for_context_mcp/server.py
ask_human_for_context_mcp-1.0.2.dist-info/METADATA
ask_human_for_context_mcp-1.0.2.dist-info/WHEEL
ask_human_for_context_mcp-1.0.2.dist-info/entry_points.txt
ask_human_for_context_mcp-1.0.2.dist-info/licenses/LICENSE
ask_human_for_context_mcp-1.0.2.dist-info/RECORD
