Metadata-Version: 2.4
Name: ask-human-for-context-mcp
Version: 1.0.2
Summary: Ask Human for Context MCP Server - GUI dialogs for AI assistant interaction
Project-URL: Homepage, https://github.com/galperetz/ask-human-for-context-mcp
Project-URL: Repository, https://github.com/galperetz/ask-human-for-context-mcp
Project-URL: Issues, https://github.com/galperetz/ask-human-for-context-mcp/issues
Author-email: Gal Peretz <gal@example.com>
License: MIT
License-File: LICENSE
Keywords: ai-assistant,ask-human-for-context,cursor,dialog,gui,mcp
Classifier: Development Status :: 5 - Production/Stable
Classifier: Intended Audience :: Developers
Classifier: License :: OSI Approved :: MIT License
Classifier: Programming Language :: Python :: 3
Classifier: Programming Language :: Python :: 3.8
Classifier: Programming Language :: Python :: 3.9
Classifier: Programming Language :: Python :: 3.10
Classifier: Programming Language :: Python :: 3.11
Classifier: Programming Language :: Python :: 3.12
Classifier: Topic :: Communications :: Chat
Classifier: Topic :: Desktop Environment :: File Managers
Classifier: Topic :: Software Development :: Libraries :: Python Modules
Requires-Python: >=3.8
Requires-Dist: mcp
Provides-Extra: dev
Requires-Dist: black>=22.0.0; extra == 'dev'
Requires-Dist: isort>=5.0.0; extra == 'dev'
Requires-Dist: mypy>=1.0.0; extra == 'dev'
Requires-Dist: pytest>=7.0.0; extra == 'dev'
